dbt_webhook/__init__.py
dbt_webhook/config.py
dbt_webhook/events.py
dbt_webhook/plugin.py
dbt_webhook/webhook_model.py
dbt_webhook/dynamic_vars/__init__.py
dbt_webhook/dynamic_vars/base.py
dbt_webhook/dynamic_vars/gcp_id_token.py
dbt_webhook-0.3.6.dist-info/licenses/LICENSE
dbt_webhook-0.3.6.dist-info/METADATA
dbt_webhook-0.3.6.dist-info/WHEEL
dbt_webhook-0.3.6.dist-info/top_level.txt
dbt_webhook-0.3.6.dist-info/RECORD
