Metadata-Version: 2.4
Name: dbt-webhook
Version: 0.3.6
Summary: A DBT plugin that allows defining HTTP hooks for DBT commands and/or models, triggering them at execution start/end, and injecting the returned data into the model's metadata.
Author-email: DataEng AI <dataeng.ai@gmail.com>
Requires-Python: >=3.9
License-File: LICENSE
Requires-Dist: dbt-core>=1.7.0
Requires-Dist: requests>=2.25.0
Dynamic: license-file
